revelation/__init__.py
revelation/app.py
revelation/cli.py
revelation/cli_types.py
revelation/config.py
revelation/constants.py
revelation/default_config.py
revelation/py.typed
revelation/utils.py
revelation/templates/presentation.html
revelation-2.3.1.dist-info/METADATA
revelation-2.3.1.dist-info/WHEEL
revelation-2.3.1.dist-info/entry_points.txt
revelation-2.3.1.dist-info/licenses/LICENSE
revelation-2.3.1.dist-info/RECORD
