Metadata-Version: 2.4
Name: revelation
Version: 2.3.1
Summary: Make awesome reveal.js presentations with revelation
Project-URL: Documentation, https://github.com/humrochagf/revelation
Project-URL: Issues, https://github.com/humrochagf/revelation/issues
Project-URL: Source, https://github.com/humrochagf/revelation
Author-email: Humberto Rocha <humrochagf@gmail.com>
License-Expression: MIT
License-File: LICENSE
Keywords: cli,presentation,reveal.js,slides
Classifier: Environment :: Console
Classifier: Programming Language :: Python
Classifier: Programming Language :: Python :: 3.10
Classifier: Programming Language :: Python :: 3.11
Classifier: Programming Language :: Python :: 3.12
Classifier: Programming Language :: Python :: 3.13
Classifier: Programming Language :: Python :: Implementation :: CPython
Classifier: Programming Language :: Python :: Implementation :: PyPy
Classifier: Topic :: Text Processing :: Markup :: Markdown
Requires-Python: >=3.10
Requires-Dist: jinja2~=3.1.6
Requires-Dist: platformdirs~=4.3.8
Requires-Dist: typer~=0.16.0
Requires-Dist: werkzeug[watchdog]~=3.1.3
